{"chunk_definitions":[{"row":30,"row_count":1,"visible":true,"expansion_state":0,"options":{"engine":"r","label":"unnamed-chunk-6"},"document_id":"8D57D28A","chunk_id":"c14rvhft1onul","chunk_label":"unnamed-chunk-1"},{"row":380,"row_count":1,"visible":true,"expansion_state":0,"options":{"engine":"r","label":"unnamed-chunk-71"},"document_id":"8D57D28A","chunk_id":"cdhtm5rxuh20g","chunk_label":"unnamed-chunk-6"},{"row":452,"row_count":1,"visible":true,"expansion_state":0,"options":{"engine":"r","label":"unnamed-chunk-94"},"document_id":"8D57D28A","chunk_id":"cg2kj9jefy0kd","chunk_label":"unnamed-chunk-7"},{"row":512,"row_count":1,"visible":true,"expansion_state":0,"options":{},"document_id":"8D57D28A","chunk_id":"clquahbee0mwe","chunk_label":"unnamed-chunk-8"}],"doc_write_time":1668201977}